openstf_dbc/__init__.py
openstf_dbc/__main__.py
openstf_dbc/data_interface.py
openstf_dbc/database.py
openstf_dbc/ktp_api.py
openstf_dbc/utils.py
openstf_dbc/config/__init__.py
openstf_dbc/config/builder.py
openstf_dbc/config/config.py
openstf_dbc/config/enums.py
openstf_dbc/config/utils.py
openstf_dbc/log/__init__.py
openstf_dbc/log/logging.py
openstf_dbc/log/processors.py
openstf_dbc/models/__init__.py
openstf_dbc/models/measurement.py
openstf_dbc/models/switch_state.py
openstf_dbc/services/__init__.py
openstf_dbc/services/ems.py
openstf_dbc/services/model_input.py
openstf_dbc/services/prediction_job.py
openstf_dbc/services/predictions.py
openstf_dbc/services/predictor.py
openstf_dbc/services/splitting.py
openstf_dbc/services/systems.py
openstf_dbc/services/weather.py
openstf_dbc/services/write.py
openstf_dbc-2.2.0.dist-info/LICENSE
openstf_dbc-2.2.0.dist-info/METADATA
openstf_dbc-2.2.0.dist-info/WHEEL
openstf_dbc-2.2.0.dist-info/top_level.txt
openstf_dbc-2.2.0.dist-info/RECORD
