Metadata-Version: 2.1
Name: openstf-dbc
Version: 2.2.0
Summary: Database Connection for OpenSTF
Home-page: https://github.com/alliander-opensource/openstf-dbc
Author: Alliander N.V
Author-email: korte.termijn.prognoses@alliander.com
License: MPL-2.0
Keywords: database,energy,forecasting,machinelearning
Platform: UNKNOWN
Classifier: Development Status :: 5 - Production/Stable
Classifier: Intended Audience :: Developers
Classifier: License :: OSI Approved :: Mozilla Public License 2.0 (MPL 2.0)
Classifier: Programming Language :: Python :: 3.7
Classifier: Programming Language :: Python :: 3.8
Classifier: Programming Language :: Python :: 3.9
Requires-Python: >=3.7.0
License-File: LICENSE
Requires-Dist: geopy (~=2.1.0)
Requires-Dist: influxdb (~=5.2.3)
Requires-Dist: mysql-connector-python (~=8.0.23)
Requires-Dist: numpy (~=1.20.1)
Requires-Dist: pandas (~=1.2.4)
Requires-Dist: PyMySQL (~=1.0.2)
Requires-Dist: PyYAML (~=5.4.1)
Requires-Dist: requests (~=2.25.1)
Requires-Dist: SQLAlchemy (~=1.3.16)
Requires-Dist: structlog (~=20.2.0)
Requires-Dist: pydantic (~=1.8.2)
